cshogi-0.9.7.dist-info/LICENSE
cshogi-0.9.7.dist-info/RECORD
cshogi-0.9.7.dist-info/WHEEL
cshogi-0.9.7.dist-info/top_level.txt
cshogi-0.9.7.dist-info/METADATA
cshogi/KI2.py
cshogi/KIF.py
cshogi/__init__.py
cshogi/elo.py
cshogi/PGN.py
cshogi/cli.py
cshogi/_cshogi.cpython-310-x86_64-linux-gnu.so
cshogi/CSA.py
cshogi/_cshogi.pyx
cshogi/_cshogi.cpp
cshogi/usi/__init__.py
cshogi/usi/Engine.py
cshogi/gym_shogi/__init__.py
cshogi/gym_shogi/envs/shogi_env.cpython-310-x86_64-linux-gnu.so
cshogi/gym_shogi/envs/__init__.py
cshogi/gym_shogi/envs/shogi_vec_env.pyx
cshogi/gym_shogi/envs/shogi_env.pyx
cshogi/gym_shogi/envs/shogi_env.cpp
cshogi/gym_shogi/envs/shogi_vec_env.cpython-310-x86_64-linux-gnu.so
cshogi/gym_shogi/envs/shogi_vec_env.cpp
cshogi/dlshogi/__init__.py
cshogi/web/__init__.py
cshogi/web/app.py
cshogi/web/static/board.js
cshogi/web/templates/board.html
